LICENSE
MANIFEST.in
README.rst
requirements.txt
setup.py
src/refdoc/__init__.py
src/refdoc/cli.py
src/refdoc/logic.py
src/refdoc/rst.py
src/refdoc/toctree.py
src/refdoc/util.py
src/refdoc/objects/__init__.py
src/refdoc/objects/base.py
src/refdoc/objects/module.py
src/refdoc/objects/package.py
src/sphinx_refdoc.egg-info/PKG-INFO
src/sphinx_refdoc.egg-info/SOURCES.txt
src/sphinx_refdoc.egg-info/dependency_links.txt
src/sphinx_refdoc.egg-info/entry_points.txt
src/sphinx_refdoc.egg-info/requires.txt
src/sphinx_refdoc.egg-info/top_level.txt