Metadata-Version: 1.1
Name: sphinx-refdoc
Version: 0.3
Summary: Reference documentation generator for sphinx
Home-page: https://github.com/novopl/sphinx-refdoc
Author: Mateusz 'novo' Klos
Author-email: novopl@gmail.com
License: MIT
Platform: UNKNOWN
Classifier: Development Status :: 2 - Pre-Alpha
Classifier: Topic :: Utilities
Classifier: Intended Audience :: Developers
Classifier: Programming Language :: Python
Classifier: License :: OSI Approved :: MIT License
